physlab/__init__.py
physlab/__version__.py
physlab/core.py
physlab/test.py
physlab/test2.py
physlab-1.0.8.dist-info/licenses/LICENSE
physlab-1.0.8.dist-info/METADATA
physlab-1.0.8.dist-info/WHEEL
physlab-1.0.8.dist-info/top_level.txt
physlab-1.0.8.dist-info/RECORD
