Metadata-Version: 2.4
Name: physlab
Version: 1.0.8
Summary: Library for physical quantities with automatic uncertainty propagation
Author-email: Vsevolod Filippov <filippov.va@phystech.edu>
License: MIT
Project-URL: Homepage, https://github.com/FF170/physlab
Project-URL: Bug Reports, https://github.com/FF170/physlab/issues
Project-URL: Source, https://github.com/FF170/physlab
Keywords: physics,uncertainty,error propagation,scientific computing
Classifier: Development Status :: 4 - Beta
Classifier: Intended Audience :: Education
Classifier: Intended Audience :: Science/Research
Classifier: License :: OSI Approved :: MIT License
Classifier: Programming Language :: Python :: 3
Classifier: Topic :: Scientific/Engineering :: Physics
Classifier: Topic :: Education
Requires-Python: >=3.7
License-File: LICENSE
Requires-Dist: numpy>=1.19.0
Requires-Dist: matplotlib>=3.3.0
Dynamic: license-file
